IDsys/ID.py
IDsys/__init__.py
IDsys-0.0.9.dist-info/LICENSE
IDsys-0.0.9.dist-info/METADATA
IDsys-0.0.9.dist-info/WHEEL
IDsys-0.0.9.dist-info/top_level.txt
IDsys-0.0.9.dist-info/RECORD
