Metadata-Version: 2.1
Name: IDsys
Version: 0.0.9
Summary: Creating systeme of identification
Home-page: https://github.com/Creariax5/IDlib
Author: Florian Demartini
Author-email: florian.demartini.dev@gmail.com
Project-URL: Bug Tracker, https://github.com/Creariax5/IDlib/issues
Classifier: Programming Language :: Python :: 3
Classifier: License :: OSI Approved :: MIT License
Classifier: Operating System :: OS Independent
Requires-Python: >=3.6
License-File: LICENSE
